bigpipe_response/__init__.py
bigpipe_response/bigpipe.py
bigpipe_response/bigpipe_render_options.py
bigpipe_response/bigpipe_response.py
bigpipe_response/content_loader.py
bigpipe_response/content_result.py
bigpipe_response/decorators.py
bigpipe_response/dependencies_marshalling.py
bigpipe_response/exceptions.py
bigpipe_response/helpers.py
bigpipe_response/javascript_manager.py
bigpipe_response/pagelet.py
bigpipe_response/processors_manager.py
bigpipe_response/conf/__init__.py
bigpipe_response/conf/bigpipe.yaml
bigpipe_response/conf/bigpipe_settings.py
bigpipe_response/debugger/__init__.py
bigpipe_response/debugger/bigpipe_debugger.py
bigpipe_response/debugger/debugger.css
bigpipe_response/debugger/debugger.html
bigpipe_response/javascript_dom_bind/__init__.py
bigpipe_response/javascript_dom_bind/javascript_dom_bind.py
bigpipe_response/javascript_dom_bind/react_dom_bind.py
bigpipe_response/js/BaseProcessor.js
bigpipe_response/js/BigpipeProcessorManager.js
bigpipe_response/js/RollupBaseBuild.js
bigpipe_response/js/__init__.py
bigpipe_response/js/index.js
bigpipe_response/js/package.json
bigpipe_response/js/test_bundlers.js
bigpipe_response/js/utils.js
bigpipe_response/js/.cache/17/28c5c9cb87e610e5029281336b068e.json
bigpipe_response/js/.cache/2d/67d93f51d0c663b054381747b0f4c9.json
bigpipe_response/js/.cache/42/d1ef88dcb60ae271b5618fa6f0f21d.json
bigpipe_response/js/.cache/8b/488bb4b87b5da1ee724878bec167ec.json
bigpipe_response/js/.cache/dc/a57ace283d094b76a59d4b4f235325.json
bigpipe_response/js/.cache/f4/90de3a178dad51be126f5f30d988aa.json
bigpipe_response/js/__pycache__/__init__.cpython-36.pyc
bigpipe_response/js/__pycache__/__init__.cpython-37.pyc
bigpipe_response/js/__pycache__/test_bundlers.cpython-37.pyc
bigpipe_response/js/browser/bigpipe.js
bigpipe_response/js/browser/jsi18n.js
bigpipe_response/js/build/bigpipe_response-1.0.0.tgz
bigpipe_response/js/build/package.json
bigpipe_response/js/registered_processors/empty.txt
bigpipe_response-0.0.10a3.dist-info/LICENSE
bigpipe_response-0.0.10a3.dist-info/METADATA
bigpipe_response-0.0.10a3.dist-info/WHEEL
bigpipe_response-0.0.10a3.dist-info/top_level.txt
bigpipe_response-0.0.10a3.dist-info/RECORD
