Metadata-Version: 2.1
Name: bigpipe-response
Version: 0.0.10a3
Summary: Bigpipe, Pipelining web pages for high performance, django response object
Home-page: https://github.com/shacoshe/bigpipe-response
Author: Shay Tessler
Author-email: shay.te@gmail.com
License: MIT
Platform: UNKNOWN
Classifier: Programming Language :: Python :: 3
Classifier: License :: OSI Approved :: MIT License
Classifier: Operating System :: OS Independent
Requires-Python: >=3.7
Requires-Dist: django
Requires-Dist: libsass
Requires-Dist: watchdog
Requires-Dist: ansi2html
Requires-Dist: requests
Requires-Dist: pre-commit
Requires-Dist: hydra-core
